test/tri_test.py
test/__init__.py
test/tet_test.py
test/small_tet_test.py
wildmeshing/__init__.py
wildmeshing/triangulate_svg.py
wildmeshing/wildmeshing.cpython-312-darwin.so
wildmeshing/runners.py
wildmeshing/parse_svg/__init__.py
wildmeshing/parse_svg/setup.py
wildmeshing/parse_svg/test/test_parsing.py
wildmeshing/parse_svg/test/test_polytools.py
wildmeshing/parse_svg/test/test_sax_groups.py
wildmeshing/parse_svg/test/__init__.py
wildmeshing/parse_svg/test/test_svg2paths.py
wildmeshing/parse_svg/test/test_path.py
wildmeshing/parse_svg/test/test_bezier.py
wildmeshing/parse_svg/test/test_groups.py
wildmeshing/parse_svg/test/test_generation.py
wildmeshing/parse_svg/svgpathtools/bezier.py
wildmeshing/parse_svg/svgpathtools/__init__.py
wildmeshing/parse_svg/svgpathtools/parser.py
wildmeshing/parse_svg/svgpathtools/svg_io_sax.py
wildmeshing/parse_svg/svgpathtools/polytools.py
wildmeshing/parse_svg/svgpathtools/document.py
wildmeshing/parse_svg/svgpathtools/smoothing.py
wildmeshing/parse_svg/svgpathtools/misctools.py
wildmeshing/parse_svg/svgpathtools/paths2svg.py
wildmeshing/parse_svg/svgpathtools/path.py
wildmeshing/parse_svg/svgpathtools/svg_to_paths.py
wildmeshing/.dylibs/libgmp.10.dylib
wildmeshing/.dylibs/libtbb.12.12.dylib
wildmeshing-0.4.1.dist-info/LICENSES_bundled
wildmeshing-0.4.1.dist-info/RECORD
wildmeshing-0.4.1.dist-info/LICENSE
wildmeshing-0.4.1.dist-info/WHEEL
wildmeshing-0.4.1.dist-info/entry_points.txt
wildmeshing-0.4.1.dist-info/top_level.txt
wildmeshing-0.4.1.dist-info/METADATA
